nlptklzxcv/__init__.py
nlptklzxcv/loader.py
nlptklzxcv/data/sample1.txt
nlptklzxcv/data/streamlitx.txt
nlptklzxcv-0.4.7.dist-info/LICENSE
nlptklzxcv-0.4.7.dist-info/METADATA
nlptklzxcv-0.4.7.dist-info/WHEEL
nlptklzxcv-0.4.7.dist-info/top_level.txt
nlptklzxcv-0.4.7.dist-info/RECORD
