Metadata-Version: 2.1
Name: nlptklzxcv
Version: 0.4.7
Summary: A simple library that serves bundled text files.
Author-email: Your Name <your@email.com>
License: MIT
Requires-Python: >=3.8
License-File: LICENSE
